pygoa/__init__.py
pygoa/pygoa.py
pygoa_gemini-1.0.0.dist-info/LICENSE
pygoa_gemini-1.0.0.dist-info/METADATA
pygoa_gemini-1.0.0.dist-info/WHEEL
pygoa_gemini-1.0.0.dist-info/top_level.txt
pygoa_gemini-1.0.0.dist-info/RECORD
