Metadata-Version: 2.1
Name: pygoa-gemini
Version: 1.0.0
Summary: A simple python library for working with the Gemini Observatory Archive APIs
Home-page: https://github.com/bryanmiller/pygoa
Author: Bryan Miller
Author-email: millerwbryan@gmail.com
License: UNKNOWN
Keywords: astronomy,astrophysics,science,fits,observatory,gemini,archive
Platform: UNKNOWN
Classifier: Intended Audience :: Science/Research
Classifier: License :: Other/Proprietary License
Classifier: Operating System :: OS Independent
Classifier: Programming Language :: Python
Classifier: Topic :: Scientific/Engineering :: Astronomy
Classifier: Topic :: Scientific/Engineering :: Physics
Requires-Dist: requests
